{"is_source_file": false, "format": "", "description": "", "external_files": [], "external_methods": [], "published": [], "classes": [], "methods": [], "calls": [], "search-terms": [], "state": 2, "file_id": 12, "knowledge_revision": 28, "git_revision": "10ab69bcd428aa8dffba5717d479f54ab9136145", "hash": "76952b112594265d2e9481c534c6b718", "format-version": 4, "code-base-name": "notes_frontend", "filename": "notes_frontend/src/index.html", "revision_history": [{"28": "10ab69bcd428aa8dffba5717d479f54ab9136145"}]}